snipwizard/__init__.py
snipwizard/decorators.py
snipwizard/ds/__init__.py
snipwizard/ds/circular_doubly_linked_list.py
snipwizard/ds/doubly_linked_list.py
snipwizard/func.py
snipwizard/option.py
snipwizard/singleton.py
snipwizard-0.1.0.dist-info/WHEEL
snipwizard-0.1.0.dist-info/METADATA
snipwizard-0.1.0.dist-info/RECORD
